slack_log_utils/__init__.py
slack_log_utils/slack_webhook_formatter.py
slack_log_utils/slack_webhook_handler.py
slack_log_utils-0.1.5.dist-info/LICENSE.txt
slack_log_utils-0.1.5.dist-info/METADATA
slack_log_utils-0.1.5.dist-info/RECORD
slack_log_utils-0.1.5.dist-info/WHEEL
slack_log_utils-0.1.5.dist-info/top_level.txt
